[
  { "provider_id": 1, "business_type_id": 1 },
  { "provider_id": 1, "business_type_id": 2 },
  { "provider_id": 2, "business_type_id": 1 },
  { "provider_id": 2, "business_type_id": 3 },
  { "provider_id": 3, "business_type_id": 1 },
  { "provider_id": 4, "business_type_id": 1 },
  { "provider_id": 4, "business_type_id": 2 },
  { "provider_id": 4, "business_type_id": 3 },
  { "provider_id": 5, "business_type_id": 1 },
  { "provider_id": 6, "business_type_id": 4 },
  { "provider_id": 7, "business_type_id": 1 },
  { "provider_id": 7, "business_type_id": 2 },
  { "provider_id": 8, "business_type_id": 5 },
  { "provider_id": 9, "business_type_id": 1 },
  { "provider_id": 9, "business_type_id": 4 },
  { "provider_id": 10, "business_type_id": 1 }
]
